md2site/__init__.py
md2site/generator.py
md2site/post.py
md2site/py.typed
md2site/renderer.py
md2site/site.py
md2site-0.0.8.dist-info/LICENSE.md
md2site-0.0.8.dist-info/METADATA
md2site-0.0.8.dist-info/WHEEL
md2site-0.0.8.dist-info/entry_points.txt
md2site-0.0.8.dist-info/RECORD
